x_twitter_thread_dump/__init__.py
x_twitter_thread_dump/__main__.py
x_twitter_thread_dump/_async.py
x_twitter_thread_dump/_base.py
x_twitter_thread_dump/_sync.py
x_twitter_thread_dump/browser.py
x_twitter_thread_dump/cli.py
x_twitter_thread_dump/consts.py
x_twitter_thread_dump/entities.py
x_twitter_thread_dump/images.py
x_twitter_thread_dump/py.typed
x_twitter_thread_dump/render.py
x_twitter_thread_dump/thread_template.html
x_twitter_thread_dump/types.py
x_twitter_thread_dump/utils.py
x_twitter_thread_dump/_api/__init__.py
x_twitter_thread_dump/_api/__main__.py
x_twitter_thread_dump/_api/app.py
x_twitter_thread_dump/_api/dependencies.py
x_twitter_thread_dump/_api/metrics.py
x_twitter_thread_dump/_api/router.py
x_twitter_thread_dump/_api/schemas.py
x_twitter_thread_dump/_api/settings.py
x_twitter_thread_dump/_api/sharable_brower_ctx.py
x_twitter_thread_dump/_api/utils.py
x_twitter_thread_dump/_api/_threads/__init__.py
x_twitter_thread_dump/_api/_threads/dependencies.py
x_twitter_thread_dump/_api/_threads/router.py
x_twitter_thread_dump/_threads/__init__.py
x_twitter_thread_dump/_threads/_async.py
x_twitter_thread_dump/_threads/consts.py
x_twitter_thread_dump/_threads/entities.py
x_twitter_thread_dump/_threads/render.py
x_twitter_thread_dump/_threads/threads_template.html
x_twitter_thread_dump-0.1.0.dist-info/METADATA
x_twitter_thread_dump-0.1.0.dist-info/WHEEL
x_twitter_thread_dump-0.1.0.dist-info/entry_points.txt
x_twitter_thread_dump-0.1.0.dist-info/licenses/LICENSE
x_twitter_thread_dump-0.1.0.dist-info/RECORD
