Metadata-Version: 2.4
Name: x-twitter-thread-dump
Version: 0.1.0
Summary: A tool to dump threads and media from X (formerly Twitter).
License-File: LICENSE
Requires-Python: >=3.13
Requires-Dist: click>=8.2.1
Requires-Dist: httpx>=0.28.1
Requires-Dist: jinja2>=3.1.6
Requires-Dist: more-itertools>=10.7.0
Requires-Dist: pillow>=11.2.1
Requires-Dist: playwright>=1.52.0
Requires-Dist: xclienttransaction>=1.0.0
Provides-Extra: server
Requires-Dist: aiorwlock>=1.5.0; extra == 'server'
Requires-Dist: fastapi>=0.115.12; extra == 'server'
Requires-Dist: logfire[fastapi,httpx,system-metrics]>=3.21.1; extra == 'server'
Requires-Dist: pydantic-settings>=2.9.1; extra == 'server'
Requires-Dist: pydantic>=2.9.1; extra == 'server'
Requires-Dist: uvicorn>=0.34.2; extra == 'server'
